netvisor_api_client/__init__.py
netvisor_api_client/auth.py
netvisor_api_client/client.py
netvisor_api_client/core.py
netvisor_api_client/exc.py
netvisor_api_client/requestmodels/__init__.py
netvisor_api_client/requestmodels/accounting.py
netvisor_api_client/requestmodels/base.py
netvisor_api_client/requestmodels/company.py
netvisor_api_client/requestmodels/customer.py
netvisor_api_client/requestmodels/dimension.py
netvisor_api_client/requestmodels/product.py
netvisor_api_client/requestmodels/purchase_invoice.py
netvisor_api_client/requestmodels/sales_invoice.py
netvisor_api_client/requestmodels/sales_payment.py
netvisor_api_client/responsemodels/__init__.py
netvisor_api_client/responsemodels/accounting.py
netvisor_api_client/responsemodels/base.py
netvisor_api_client/responsemodels/companies.py
netvisor_api_client/responsemodels/customers.py
netvisor_api_client/responsemodels/dimensions.py
netvisor_api_client/responsemodels/products.py
netvisor_api_client/responsemodels/purchase_invoices.py
netvisor_api_client/responsemodels/sales_invoices.py
netvisor_api_client/responsemodels/sales_payments.py
netvisor_api_client/schemas/__init__.py
netvisor_api_client/schemas/common.py
netvisor_api_client/schemas/fields.py
netvisor_api_client/schemas/replies.py
netvisor_api_client/schemas/accounting/__init__.py
netvisor_api_client/schemas/accounting/accountlist.py
netvisor_api_client/schemas/accounting/create.py
netvisor_api_client/schemas/accounting/ledger.py
netvisor_api_client/schemas/accounting/periodlist.py
netvisor_api_client/schemas/companies/__init__.py
netvisor_api_client/schemas/companies/get.py
netvisor_api_client/schemas/companies/list.py
netvisor_api_client/schemas/customers/__init__.py
netvisor_api_client/schemas/customers/create.py
netvisor_api_client/schemas/customers/get.py
netvisor_api_client/schemas/customers/list.py
netvisor_api_client/schemas/dimensions/__init__.py
netvisor_api_client/schemas/dimensions/create.py
netvisor_api_client-0.9.6.dist-info/licenses/LICENSE
netvisor_api_client-0.9.6.dist-info/METADATA
netvisor_api_client-0.9.6.dist-info/WHEEL
netvisor_api_client-0.9.6.dist-info/top_level.txt
netvisor_api_client-0.9.6.dist-info/RECORD
