Metadata-Version: 2.4
Name: netvisor-api-client
Version: 0.9.6
Summary: # Netvisor: Python API client
Home-page: https://github.com/Heltti/netvisor-api-client
Author: Heltti Oy
Author-email: dev@heltti.fi
License: The MIT License (MIT)
Platform: any
Classifier: Development Status :: 3 - Alpha
Classifier: Intended Audience :: Developers
Classifier: License :: OSI Approved :: MIT License
Classifier: Operating System :: OS Independent
Classifier: Programming Language :: Python
Classifier: Programming Language :: Python :: 3
Classifier: Programming Language :: Python :: 3.11
Classifier: Programming Language :: Python :: 3.12
Classifier: Programming Language :: Python :: 3.13
Classifier: Topic :: Software Development :: Libraries :: Python Modules
License-File: LICENSE
Requires-Dist: inflection
Requires-Dist: marshmallow<3.0.0
Requires-Dist: responses
Requires-Dist: requests
Requires-Dist: xmltodict>=0.10.1
Dynamic: author
Dynamic: author-email
Dynamic: classifier
Dynamic: description
Dynamic: description-content-type
Dynamic: home-page
Dynamic: license
Dynamic: license-file
Dynamic: platform
Dynamic: requires-dist
Dynamic: summary
